Metadata-Version: 1.0
Name: markdown2latex
Version: 1.2
Summary: Extension
Home-page: http://www.okfn.org/okftext/
Author: Rufus Pollock (Open Knowledge Foundation)
Author-email: rufus [at] rufuspollock [dot] org
License: MIT
Download-URL: http://knowledgeforge.net/okftext/svn/trunk/python/mdx_latex/
Keywords: latex markdown python
Platform: UNKNOWN
Classifier: Development Status :: 5 - Production/Stable
Classifier: Environment :: Console
Classifier: Intended Audience :: Developers
Classifier: License :: OSI Approved :: BSD License
Classifier: Operating System :: OS Independent
Classifier: Programming Language :: Python
Classifier: Topic :: Software Development :: Libraries :: Python Modules
